fluid/__init__.py
fluid/db/__init__.py
fluid/db/cli.py
fluid/db/container.py
fluid/db/crud.py
fluid/db/cursor.py
fluid/db/migration.py
fluid/db/pagination.py
fluid/py.typed
fluid/scheduler/__init__.py
fluid/scheduler/broker.py
fluid/scheduler/cli.py
fluid/scheduler/common.py
fluid/scheduler/consumer.py
fluid/scheduler/cpubound.py
fluid/scheduler/endpoints.py
fluid/scheduler/errors.py
fluid/scheduler/k8s_job.py
fluid/scheduler/models.py
fluid/scheduler/scheduler.py
fluid/scheduler/scheduler_crontab.py
fluid/scheduler/scheduler_every.py
fluid/settings.py
fluid/tools_fastapi/__init__.py
fluid/tools_fastapi/backdoor.py
fluid/tools_fastapi/service.py
fluid/utils/__init__.py
fluid/utils/backdoor.py
fluid/utils/data.py
fluid/utils/dates.py
fluid/utils/dispatcher.py
fluid/utils/errors.py
fluid/utils/http_client.py
fluid/utils/http_monitor.py
fluid/utils/json2.py
fluid/utils/kernel.py
fluid/utils/lazy.py
fluid/utils/log.py
fluid/utils/redis.py
fluid/utils/stacksampler.py
fluid/utils/text.py
fluid/utils/waiter.py
fluid/utils/worker.py
aio_fluid-1.6.2.dist-info/LICENSE
aio_fluid-1.6.2.dist-info/METADATA
aio_fluid-1.6.2.dist-info/WHEEL
aio_fluid-1.6.2.dist-info/RECORD
