Metadata-Version: 2.3
Name: aio-fluid
Version: 1.6.2
Summary: Tools for backend python services
License: BSD
Author: Luca Sbardella
Author-email: luca@quantmind.com
Requires-Python: >=3.11,<4.0
Classifier: License :: Other/Proprietary License
Classifier: Programming Language :: Python :: 3
Classifier: Programming Language :: Python :: 3.11
Classifier: Programming Language :: Python :: 3.12
Classifier: Programming Language :: Python :: 3.13
Provides-Extra: cli
Provides-Extra: db
Provides-Extra: http
Provides-Extra: k8s
Provides-Extra: log
Requires-Dist: aioconsole (>=0.8.0)
Requires-Dist: aiohttp (>=3.10.10) ; extra == "http"
Requires-Dist: alembic (>=1.13.2) ; extra == "db"
Requires-Dist: asyncpg (>=0.30.0) ; extra == "db"
Requires-Dist: click (>=8.1.7) ; extra == "cli"
Requires-Dist: click (>=8.1.7) ; extra == "db"
Requires-Dist: fastapi (>=0.115.2)
Requires-Dist: httpx (>=0.28.1) ; extra == "http"
Requires-Dist: inflection (>=0.5.1)
Requires-Dist: kubernetes (>=32.0.0) ; extra == "k8s"
Requires-Dist: kubernetes-asyncio (>=32.0.0) ; extra == "k8s"
Requires-Dist: prometheus-client (>=0.21.0) ; extra == "http"
Requires-Dist: psycopg2-binary (>=2.9.9) ; extra == "db"
Requires-Dist: pydanclick (>=0.5.0) ; extra == "cli"
Requires-Dist: pydanclick (>=0.5.0) ; extra == "db"
Requires-Dist: pydantic (>=2.9.2)
Requires-Dist: python-dateutil (>=2.9.0) ; extra == "db"
Requires-Dist: python-json-logger (>=3.2.1) ; extra == "log"
Requires-Dist: python-slugify (>=8.0.4) ; extra == "http"
Requires-Dist: python-slugify (>=8.0.4) ; extra == "k8s"
Requires-Dist: redis[hiredis] (>=5.0.1)
Requires-Dist: rich (>=13.7.1) ; extra == "cli"
Requires-Dist: rich (>=13.7.1) ; extra == "db"
Requires-Dist: sqlalchemy (>=2.0.23) ; extra == "db"
Requires-Dist: sqlalchemy-utils (>=0.41.2) ; extra == "db"
Requires-Dist: typing-extensions (>=4.12.2)
Requires-Dist: uvicorn (>=0.34.0)
Requires-Dist: yarl (>=1.15.5)
Project-URL: Issues, https://github.com/quantmind/aio-fluid/issues
Project-URL: Repository, https://github.com/quantmind/aio-fluid
